MANIFEST.in
README.md
setup.py
dbt/__init__.py
dbt/adapters/__init__.py
dbt/adapters/cockroachdb/__init__.py
dbt/adapters/cockroachdb/column.py
dbt/adapters/cockroachdb/connections.py
dbt/adapters/cockroachdb/impl.py
dbt/adapters/cockroachdb/relation.py
dbt/adapters/cockroachdb/relation_configs/__init__.py
dbt/adapters/cockroachdb/relation_configs/constants.py
dbt/adapters/cockroachdb/relation_configs/index.py
dbt/adapters/cockroachdb/relation_configs/materialized_view.py
dbt/include/cockroachdb/__init__.py
dbt/include/cockroachdb/dbt_project.yml
dbt/include/cockroachdb/profile_template.yml
dbt/include/cockroachdb/sample_profiles.yml
dbt/include/cockroachdb/macros/adapters.sql
dbt/include/cockroachdb/macros/catalog.sql
dbt/include/cockroachdb/macros/relations.sql
dbt/include/cockroachdb/macros/timestamps.sql
dbt/include/cockroachdb/macros/materializations/incremental_strategies.sql
dbt/include/cockroachdb/macros/materializations/snapshot_merge.sql
dbt/include/cockroachdb/macros/relations/materialized_view/alter.sql
dbt/include/cockroachdb/macros/relations/materialized_view/create.sql
dbt/include/cockroachdb/macros/relations/materialized_view/describe.sql
dbt/include/cockroachdb/macros/relations/materialized_view/drop.sql
dbt/include/cockroachdb/macros/relations/materialized_view/refresh.sql
dbt/include/cockroachdb/macros/relations/materialized_view/rename.sql
dbt/include/cockroachdb/macros/relations/table/drop.sql
dbt/include/cockroachdb/macros/relations/table/rename.sql
dbt/include/cockroachdb/macros/relations/table/replace.sql
dbt/include/cockroachdb/macros/relations/view/drop.sql
dbt/include/cockroachdb/macros/relations/view/rename.sql
dbt/include/cockroachdb/macros/relations/view/replace.sql
dbt/include/cockroachdb/macros/utils/any_value.sql
dbt/include/cockroachdb/macros/utils/columns_spec_ddl.sql
dbt/include/cockroachdb/macros/utils/dateadd.sql
dbt/include/cockroachdb/macros/utils/datediff.sql
dbt/include/cockroachdb/macros/utils/last_day.sql
dbtx_cockroachdb.egg-info/PKG-INFO
dbtx_cockroachdb.egg-info/SOURCES.txt
dbtx_cockroachdb.egg-info/dependency_links.txt
dbtx_cockroachdb.egg-info/not-zip-safe
dbtx_cockroachdb.egg-info/requires.txt
dbtx_cockroachdb.egg-info/top_level.txt